blesta_sdk/__init__.py
blesta_sdk/api/__init__.py
blesta_sdk/api/blesta_request.py
blesta_sdk/cli/__init__.py
blesta_sdk/cli/blesta_cli.py
blesta_sdk/core/__init__.py
blesta_sdk/core/blesta_response.py
blesta_sdk-0.1.6.dist-info/METADATA
blesta_sdk-0.1.6.dist-info/WHEEL
blesta_sdk-0.1.6.dist-info/entry_points.txt
blesta_sdk-0.1.6.dist-info/licenses/LICENSE
blesta_sdk-0.1.6.dist-info/RECORD
