Metadata-Version: 2.4
Name: blesta_sdk
Version: 0.1.6
Summary: A SDK for integrating with Blesta
Author: jwogrady
License-File: LICENSE
Requires-Python: >=3.9
Requires-Dist: python-dotenv>=1.0.1
Requires-Dist: requests>=2.32.3
